<annotation verified="yes">
	<folder>sard_labelImg</folder>
	<filename>gss212.jpg</filename>
	<path>/home/gss/labelImg/sard_labelImg/gss212.jpg</path>
	<source>
		<database>Unknown</database>
	</source>
	<size>
		<width>1920</width>
		<height>1080</height>
		<depth>3</depth>
	</size>
	<segmented>0</segmented>
	<object>
		<name>not_defined</name>
		<pose>Unspecified</pose>
		<truncated>0</truncated>
		<difficult>0</difficult>
		<bndbox>
			<xmin>122</xmin>
			<ymin>350</ymin>
			<xmax>173</xmax>
			<ymax>390</ymax>
		</bndbox>
	</object>
	<object>
		<name>person</name>
		<pose>Unspecified</pose>
		<truncated>0</truncated>
		<difficult>0</difficult>
		<bndbox>
			<xmin>1763</xmin>
			<ymin>921</ymin>
			<xmax>1847</xmax>
			<ymax>981</ymax>
		</bndbox>
	</object>
	<object>
		<name>person</name>
		<pose>Unspecified</pose>
		<truncated>0</truncated>
		<difficult>0</difficult>
		<bndbox>
			<xmin>1006</xmin>
			<ymin>834</ymin>
			<xmax>1060</xmax>
			<ymax>903</ymax>
		</bndbox>
	</object>
</annotation>
