<annotation verified="yes">
	<folder>sard_labelImg</folder>
	<filename>gss463.jpg</filename>
	<path>/home/gss/labelImg/sard_labelImg/gss463.jpg</path>
	<source>
		<database>Unknown</database>
	</source>
	<size>
		<width>1920</width>
		<height>1080</height>
		<depth>3</depth>
	</size>
	<segmented>0</segmented>
	<object>
		<name>person</name>
		<pose>Unspecified</pose>
		<truncated>0</truncated>
		<difficult>0</difficult>
		<bndbox>
			<xmin>535</xmin>
			<ymin>527</ymin>
			<xmax>632</xmax>
			<ymax>608</ymax>
		</bndbox>
	</object>
	<object>
		<name>not_defined</name>
		<pose>Unspecified</pose>
		<truncated>0</truncated>
		<difficult>0</difficult>
		<bndbox>
			<xmin>106</xmin>
			<ymin>113</ymin>
			<xmax>164</xmax>
			<ymax>157</ymax>
		</bndbox>
	</object>
	<object>
		<name>person</name>
		<pose>Unspecified</pose>
		<truncated>0</truncated>
		<difficult>0</difficult>
		<bndbox>
			<xmin>4</xmin>
			<ymin>95</ymin>
			<xmax>67</xmax>
			<ymax>118</ymax>
		</bndbox>
	</object>
</annotation>
