<annotation verified="yes">
	<folder>sard_labelImg</folder>
	<filename>gss636.jpg</filename>
	<path>/home/gss/labelImg/sard_labelImg/gss636.jpg</path>
	<source>
		<database>Unknown</database>
	</source>
	<size>
		<width>1920</width>
		<height>1080</height>
		<depth>3</depth>
	</size>
	<segmented>0</segmented>
	<object>
		<name>person</name>
		<pose>Unspecified</pose>
		<truncated>0</truncated>
		<difficult>0</difficult>
		<bndbox>
			<xmin>242</xmin>
			<ymin>643</ymin>
			<xmax>401</xmax>
			<ymax>699</ymax>
		</bndbox>
	</object>
	<object>
		<name>person</name>
		<pose>Unspecified</pose>
		<truncated>0</truncated>
		<difficult>0</difficult>
		<bndbox>
			<xmin>325</xmin>
			<ymin>647</ymin>
			<xmax>374</xmax>
			<ymax>680</ymax>
		</bndbox>
	</object>
	<object>
		<name>person</name>
		<pose>Unspecified</pose>
		<truncated>0</truncated>
		<difficult>0</difficult>
		<bndbox>
			<xmin>275</xmin>
			<ymin>648</ymin>
			<xmax>332</xmax>
			<ymax>677</ymax>
		</bndbox>
	</object>
	<object>
		<name>person</name>
		<pose>Unspecified</pose>
		<truncated>0</truncated>
		<difficult>0</difficult>
		<bndbox>
			<xmin>1195</xmin>
			<ymin>462</ymin>
			<xmax>1212</xmax>
			<ymax>523</ymax>
		</bndbox>
	</object>
	<object>
		<name>person</name>
		<pose>Unspecified</pose>
		<truncated>0</truncated>
		<difficult>0</difficult>
		<bndbox>
			<xmin>1175</xmin>
			<ymin>472</ymin>
			<xmax>1218</xmax>
			<ymax>496</ymax>
		</bndbox>
	</object>
	<object>
		<name>person</name>
		<pose>Unspecified</pose>
		<truncated>0</truncated>
		<difficult>0</difficult>
		<bndbox>
			<xmin>1512</xmin>
			<ymin>407</ymin>
			<xmax>1542</xmax>
			<ymax>429</ymax>
		</bndbox>
	</object>
	<object>
		<name>person</name>
		<pose>Unspecified</pose>
		<truncated>0</truncated>
		<difficult>0</difficult>
		<bndbox>
			<xmin>1771</xmin>
			<ymin>322</ymin>
			<xmax>1791</xmax>
			<ymax>372</ymax>
		</bndbox>
	</object>
</annotation>
